samseg/merge_alphas.py
samseg/__init__.py
samseg/SamsegTumor.py
samseg/color_scheme.py
samseg/SamsegLesion.py
samseg/SamsegLongitudinal.py
samseg/Samseg.py
samseg/SamsegLongitudinalLesion.py
samseg/kvl.py
samseg/VAE.py
samseg/Affine.py
samseg/GMM.py
samseg/utilities.py
samseg/warp_mesh.py
samseg/SamsegUtility.py
samseg/BiasField.py
samseg/figures.py
samseg/io.py
samseg/hdav.py
samseg/ProbabilisticAtlas.py
samseg/cli/prepareAtlasDirectory.py
samseg/cli/computeTissueConcentrations.py
samseg/gems/__init__.py
samseg/gems/gemsbindings.cpython-39-x86_64-linux-gnu.so
samseg/atlas/20Subjects_smoothing2_down2_smoothingForAffine2/photo.lh.sharedGMMParameters.txt
samseg/atlas/20Subjects_smoothing2_down2_smoothingForAffine2/atlas_level1.txt.gz
samseg/atlas/20Subjects_smoothing2_down2_smoothingForAffine2/photo.rh.sharedGMMParameters.txt
samseg/atlas/20Subjects_smoothing2_down2_smoothingForAffine2/sharedGMMParameters.txt
samseg/atlas/20Subjects_smoothing2_down2_smoothingForAffine2/atlas_level2.txt.gz
samseg/atlas/20Subjects_smoothing2_down2_smoothingForAffine2/modifiedFreeSurferColorLUT.txt
samseg/atlas/20Subjects_smoothing2_down2_smoothingForAffine2/atlasForAffineRegistration.txt.gz
samseg/atlas/20Subjects_smoothing2_down2_smoothingForAffine2/photo.both.sharedGMMParameters.txt
samseg/atlas/20Subjects_smoothing2_down2_smoothingForAffine2/tmp1.txt
samseg/atlas/20Subjects_smoothing2_down2_smoothingForAffine2/compressionLookupTable.txt
samseg/atlas/20Subjects_smoothing2_down2_smoothingForAffine2/tmp2.txt
samseg/atlas/20Subjects_smoothing2_down2_smoothingForAffine2/README
samseg/subregions/__init__.py
samseg/subregions/utils.py
samseg/subregions/core.py
samseg/subregions/hippocampus.py
samseg/subregions/brainstem.py
samseg/subregions/thalamus.py
samseg/subregions/process.py
samseg-0.1.dist-info/top_level.txt
samseg-0.1.dist-info/WHEEL
samseg-0.1.dist-info/RECORD
samseg-0.1.dist-info/METADATA
samseg-0.1.dist-info/entry_points.txt
