Metadata-Version: 2.1
Name: samseg
Version: 0.1
Summary: Sequence-Adaptive Multimodal SEGmentation (SAMSEG)
Home-page: https://github.com/freesurfer/samseg
Author: Koen Van Leemput, Oula Puonti, Juan Eugenio Iglesias, Stefano Cerri
Author-email: oulap@drcmr.dk
License: GPL3
Requires-Dist: surfa
Requires-Dist: scikit-learn
Requires-Dist: numpy
